README.md
setup.cfg
setup.py
linesend/__init__.py
linesend/linesend.py
linesend.egg-info/PKG-INFO
linesend.egg-info/SOURCES.txt
linesend.egg-info/dependency_links.txt
linesend.egg-info/entry_points.txt
linesend.egg-info/requires.txt
linesend.egg-info/top_level.txt