Metadata-Version: 1.2
Name: linesend
Version: 1.0.4
Summary: .
Home-page: https://github.com/0h-n0/linesend
Author: Koji Ono
Author-email: koji.ono@exwzd.com
License: UNKNOWN
Platform: UNKNOWN
Classifier: Programming Language :: Python :: 3.6
Requires-Python: >3.6
